simulatetraj/__init__.py
simulatetraj/simulate.py
simulatetraj-0.0.4.dist-info/LICENSE
simulatetraj-0.0.4.dist-info/METADATA
simulatetraj-0.0.4.dist-info/WHEEL
simulatetraj-0.0.4.dist-info/RECORD
