Metadata-Version: 2.1
Name: simulatetraj
Version: 0.0.4
Summary: a class to integrate ordinary differential equation
Home-page: http://simulatetraj.rtfd.io/
License: LGPL V3
Author: sandeep
Author-email: rskravi15@gmail.com
Requires-Python: >=3.10,<4.0
Classifier: License :: Other/Proprietary License
Classifier: Programming Language :: Python :: 3
Classifier: Programming Language :: Python :: 3.10
Classifier: Programming Language :: Python :: 3.11
Classifier: Programming Language :: Python :: 3.12
Requires-Dist: casadi (>=3.6.5,<4.0.0)
Requires-Dist: matplotlib (>=3.9.0,<4.0.0)
Requires-Dist: numpy (>=2.0.0,<3.0.0)
Requires-Dist: scipy (>=1.13.1,<2.0.0)
Project-URL: Repository, https://github.com/sandeep026/simulatetraj
